algo/__init__.py
algo/__main__.py
algo/_version.py
algo/call_numpy/__init__.py
algo/call_numpy/call_numpy.cpython-311-aarch64-linux-musl.so
algo/call_pandas/__init__.py
algo/call_pandas/call_pandas.cpython-311-aarch64-linux-musl.so
algo/cext/__init__.py
algo/cext/fastsum.cpython-311-aarch64-linux-musl.so
algo/func01/__init__.py
algo/func01/func01.cpython-311-aarch64-linux-musl.so
algo/func02/__init__.py
algo/func02/func02.cpython-311-aarch64-linux-musl.so
test_code/test_code.py
k_algo-0.1.17.dist-info/METADATA
k_algo-0.1.17.dist-info/WHEEL
k_algo-0.1.17.dist-info/entry_points.txt
k_algo-0.1.17.dist-info/top_level.txt
k_algo-0.1.17.dist-info/RECORD
